odoo/addons/base_country_state_translatable/README.rst
odoo/addons/base_country_state_translatable/__init__.py
odoo/addons/base_country_state_translatable/__manifest__.py
odoo/addons/base_country_state_translatable/i18n/base_country_state_translatable.pot
odoo/addons/base_country_state_translatable/i18n/da.po
odoo/addons/base_country_state_translatable/i18n/de.po
odoo/addons/base_country_state_translatable/i18n/es.po
odoo/addons/base_country_state_translatable/i18n/fr.po
odoo/addons/base_country_state_translatable/i18n/hr.po
odoo/addons/base_country_state_translatable/i18n/hr_HR.po
odoo/addons/base_country_state_translatable/i18n/it.po
odoo/addons/base_country_state_translatable/i18n/pt_BR.po
odoo/addons/base_country_state_translatable/i18n/sl.po
odoo/addons/base_country_state_translatable/models/__init__.py
odoo/addons/base_country_state_translatable/models/res_country.py
odoo/addons/base_country_state_translatable/readme/CONTRIBUTORS.rst
odoo/addons/base_country_state_translatable/readme/DESCRIPTION.rst
odoo/addons/base_country_state_translatable/readme/USAGE.rst
odoo/addons/base_country_state_translatable/static/description/icon.png
odoo/addons/base_country_state_translatable/static/description/index.html
odoo12_addon_base_country_state_translatable-12.0.1.0.0.99.dev12.dist-info/METADATA
odoo12_addon_base_country_state_translatable-12.0.1.0.0.99.dev12.dist-info/WHEEL
odoo12_addon_base_country_state_translatable-12.0.1.0.0.99.dev12.dist-info/top_level.txt
odoo12_addon_base_country_state_translatable-12.0.1.0.0.99.dev12.dist-info/RECORD
